Pratik_model/__init__.py
Pratik_model-0.1.6.dist-info/LICENSE.txt
Pratik_model-0.1.6.dist-info/METADATA
Pratik_model-0.1.6.dist-info/WHEEL
Pratik_model-0.1.6.dist-info/top_level.txt
Pratik_model-0.1.6.dist-info/RECORD
