Metadata-Version: 2.1
Name: Pratik-model
Version: 0.1.6
Summary: This package directly gives you output performance on 12 different algorithms
Home-page: 
Author: pratik
Author-email: pratikvdatey@gmail.com
License: MIT
Project-URL: source_code, https://github.com/pratikdatey/Pratik_model
Keywords: Pratik_model
Classifier: Intended Audience :: Education
Classifier: Operating System :: Microsoft :: Windows :: Windows 10
Classifier: License :: OSI Approved :: MIT License
Classifier: Programming Language :: Python :: 3
License-File: LICENSE.txt
Requires-Dist: scikit-learn
Requires-Dist: catboost
Requires-Dist: xgboost
